topsis_aditya_102303353/__init__.py
topsis_aditya_102303353/topsis.py
topsis_aditya_102303353-1.0.2.dist-info/licenses/LICENSE.txt
topsis_aditya_102303353-1.0.2.dist-info/METADATA
topsis_aditya_102303353-1.0.2.dist-info/WHEEL
topsis_aditya_102303353-1.0.2.dist-info/entry_points.txt
topsis_aditya_102303353-1.0.2.dist-info/top_level.txt
topsis_aditya_102303353-1.0.2.dist-info/RECORD
